polygon_reader/__init__.py
polygon_reader/__init__.py~
polygon_reader/reader.py
polygon_reader/reader.py~
polygon_reader-0.1.1.dist-info/METADATA
polygon_reader-0.1.1.dist-info/WHEEL
polygon_reader-0.1.1.dist-info/licenses/LICENSE
polygon_reader-0.1.1.dist-info/RECORD
